AUTHORS
LICENSE
MANIFEST.in
README.txt
setup.py
benchmark/Benchmark.py
benchmark/__init__.py
benchmark/main.py
benchmark.egg-info/PKG-INFO
benchmark.egg-info/SOURCES.txt
benchmark.egg-info/dependency_links.txt
benchmark.egg-info/not-zip-safe
benchmark.egg-info/top_level.txt
examples/benchmarkDatetimes.py
examples/benchmarkDictSorting.py
examples/benchmarkGlobs.py
examples/benchmarkPause.py
examples/benchmarkSqrt.py