Metadata-Version: 1.0
Name: benchmark
Version: 0.1.4
Summary: Python benchmarker / benchmarking framework
Home-page: http://jspi.es/benchmark
Author: Jeffrey R. Spies
Author-email: jspies@gmail.com
License: LICENSE.txt
Platform: any
Classifier: Development Status :: 4 - Beta
Classifier: Natural Language :: English
Classifier: Operating System :: OS Independent
Classifier: Intended Audience :: Developers
Classifier: Programming Language :: Python
Classifier: License :: OSI Approved :: Apache Software License
Classifier: Topic :: Software Development :: Libraries :: Python Modules
Classifier: Topic :: Software Development :: Testing
Classifier: Topic :: System :: Benchmark
